Workbook

Sheet Orders_Data
A1: Order_ID | B1: Order_Date | C1: Customer_ID | D1: Customer_Name | E1: City | F1: State | G1: Region | H1: Product_ID | I1: Product_Name | J1: Category | K1: Sub_Category | L1: Quantity | M1: Unit_Price | N1: Discount_% | O1: Sales_Amount | P1: Cost_Price | Q1: Profit | R1: Payment_Mode | S1: Sales_Channel | T1: Delivery_Status | U1: Customer_Rating | V1: Return_Status
A2: ORD0001 | B2: 46155 | C2: C1087 | D2: Karan | E2: Pune | F2: Maharashtra | G2: West | H2: P025 | I2: Shoes 25 | J2: Fashion | K2: Shoes | L2: 5 | M2: 27720 | N2: 10 | O2: 124740 | P2: 110047.41 | Q2: 14692.59 | R2: Card | S2: Offline | T2: Delivered | U2: 4 | V2: No
A3: ORD0002 | B3: 46159 | C3: C1189 | D3: Aman | E3: Chennai | F3: Tamil Nadu | G3: South | H3: P048 | I3: Shoes 48 | J3: Fashion | K3: Shoes | L3: 1 | M3: 73635 | N3: 15 | O3: 62589.75 | P3: 56147.55 | Q3: 6442.2 | R3: UPI | S3: Offline | T3: Delivered | U3: 1 | V3: Yes
A4: ORD0003 | B4: 46106 | C4: C1196 | D4: Lakshay | E4: Jaipur | F4: Rajasthan | G4: North | H4: P019 | I4: Laptop 19 | J4: Electronics | K4: Laptop | L4: 2 | M4: 73753 | N4: 0 | O4: 147506 | P4: 117588.51 | Q4: 29917.49 | R4: UPI | S4: Offline | T4: Delivered | U4: 5 | V4: Yes
A5: ORD0004 | B5: 46167 | C5: C1242 | D5: Sneha | E5: Kolkata | F5: West Bengal | G5: East | H5: P007 | I5: Laptop 7 | J5: Electronics | K5: Laptop | L5: 3 | M5: 18611 | N5: 15 | O5: 47458.05 | P5: 40125.48 | Q5: 7332.57 | R5: Cash | S5: Offline | T5: Cancelled | U5: 3 | V5: Yes
A6: ORD0005 | B6: 46076 | C6: C1251 | D6: Anjali | E6: Chennai | F6: Tamil Nadu | G6: South | H6: P064 | I6: Table 64 | J6: Furniture | K6: Table | L6: 3 | M6: 19914 | N6: 10 | O6: 53767.8 | P6: 37965.3 | Q6: 15802.5 | R6: UPI | S6: Offline | T6: Pending | U6: 1 | V6: No
A7: ORD0006 | B7: 46035 | C7: C1277 | D7: Neha | E7: Bengaluru | F7: Karnataka | G7: South | H7: P045 | I7: Chair 45 | J7: Furniture | K7: Chair | L7: 2 | M7: 44996 | N7: 20 | O7: 71993.6 | P7: 54910.48 | Q7: 17083.12 | R7: Card | S7: Online | T7: Delivered | U7: 2 | V7: No
A8: ORD0007 | B8: 46053 | C8: C1185 | D8: Neha | E8: Kolkata | F8: West Bengal | G8: East | H8: P083 | I8: Table 83 | J8: Furniture | K8: Table | L8: 3 | M8: 54196 | N8: 20 | O8: 130070.4 | P8: 106515.81 | Q8: 23554.59 | R8: Card | S8: Offline | T8: Cancelled | U8: 4 | V8: Yes
A9: ORD0008 | B9: 46097 | C9: C1105 | D9: Vikas | E9: Kolkata | F9: West Bengal | G9: East | H9: P099 | I9: Chair 99 | J9: Furniture | K9: Chair | L9: 3 | M9: 66370 | N9: 10 | O9: 179199 | P9: 163264.22 | Q9: 15934.78 | R9: Cash | S9: Online | T9: Cancelled | U9: 1 | V9: Yes
A10: ORD0009 | B10: 46040 | C10: C1179 | D10: Aman | E10: Mumbai | F10: Maharashtra | G10: West | H10: P023 | I10: Mobile 23 | J10: Electronics | K10: Mobile | L10: 4 | M10: 6035 | N10: 20 | O10: 19312 | P10: 19952.77 | Q10: -640.77 | R10: UPI | S10: Offline | T10: Delivered | U10: 3 | V10: No
A11: ORD0010 | B11: 46074 | C11: C1235 | D11: Lakshay | E11: Kolkata | F11: West Bengal | G11: East | H11: P073 | I11: Mixer 73 | J11: Home | K11: Mixer | L11: 3 | M11: 41563 | N11: 20 | O11: 99751.2 | P11: 87180.86 | Q11: 12570.34 | R11: UPI | S11: Offline | T11: Pending | U11: 1 | V11: Yes
A12: ORD0011 | B12: 46143 | C12: C1081 | D12: Aman | E12: Jaipur | F12: Rajasthan | G12: North | H12: P008 | I12: Shoes 8 | J12: Fashion | K12: Shoes | L12: 1 | M12: 60732 | N12: 20 | O12: 48585.6 | P12: 36918.16 | Q12: 11667.44 | R12: UPI | S12: Offline | T12: Pending | U12: 5 | V12: Yes
A13: ORD0012 | B13: 46151 | C13: C1219 | D13: Priya | E13: Chennai | F13: Tamil Nadu | G13: South | H13: P025 | I13: Shoes 25 | J13: Fashion | K13: Shoes | L13: 3 | M13: 56160 | N13: 5 | O13: 160056 | P13: 111084.13 | Q13: 48971.87 | R13: Card | S13: Offline | T13: Cancelled | U13: 2 | V13: No
... A1201: ORD1200 | B1201: 46179 | C1201: C1293 | D1201: Sneha | E1201: Bengaluru | F1201: Karnataka | G1201: South | H1201: P096 | I1201: Chair 96 | J1201: Furniture | K1201: Chair | L1201: 3 | M1201: 39370 | N1201: 0 | O1201: 118110 | P1201: 87927.97 | Q1201: 30182.03 | R1201: Cash | S1201: Online | T1201: Pending | U1201: 3 | V1201: No

Sheet Inventory_Data
A1: Product_ID | B1: Product_Name | C1: Category | D1: Warehouse | E1: Supplier | F1: Stock_Received | G1: Stock_Sold | H1: Current_Stock | I1: Reorder_Level | J1: Unit_Cost | K1: Selling_Price | L1: Inventory_Value | M1: Damaged_Units | N1: Lead_Time_Days | O1: Supplier_Rating | P1: Last_Restock_Date | Q1: Stock_Status
A2: P098 | B2: Mobile 98 | C2: Electronics | D2: Bengaluru WH | E2: TechCorp | F2: 363 | G2: 271 | H2: 92 | I2: 59 | J2: 42832 | K2: 57854.66 | L2: 3940544 | M2: 3 | N2: 11 | O2: 4.6 | P2: 46125 | Q2: Normal
A3: P068 | B3: Mobile 68 | C3: Electronics | D3: Kolkata WH | E3: NovaSupply | F3: 448 | G3: 178 | H3: 270 | I3: 22 | J3: 4514 | K3: 5745.92 | L3: 1218780 | M3: 0 | N3: 2 | O3: 3.8 | P3: 46138 | Q3: Normal
A4: P009 | B4: Laptop 9 | C4: Electronics | D4: Delhi WH | E4: TechCorp | F4: 207 | G4: 127 | H4: 80 | I4: 36 | J4: 32455 | K4: 38631.24 | L4: 2596400 | M4: 0 | N4: 9 | O4: 4.1 | P4: 46123 | Q4: Normal
A5: P013 | B5: Chair 13 | C5: Furniture | D5: Kolkata WH | E5: PrimeTrade | F5: 426 | G5: 81 | H5: 345 | I5: 78 | J5: 12395 | K5: 16958.49 | L5: 4276275 | M5: 5 | N5: 11 | O5: 4.9 | P5: 46184 | Q5: Normal
A6: P024 | B6: Laptop 24 | C6: Electronics | D6: Mumbai WH | E6: SupplyHub | F6: 427 | G6: 396 | H6: 31 | I6: 73 | J6: 37043 | K6: 49540.32 | L6: 1148333 | M6: 4 | N6: 9 | O6: 4.2 | P6: 46144 | Q6: Low
A7: P062 | B7: Mixer 62 | C7: Home | D7: Kolkata WH | E7: TechCorp | F7: 80 | G7: 26 | H7: 54 | I7: 40 | J7: 32165 | K7: 39372.37 | L7: 1736910 | M7: 2 | N7: 9 | O7: 3.8 | P7: 46099 | Q7: Normal
A8: P013 | B8: Chair 13 | C8: Furniture | D8: Kolkata WH | E8: TechCorp | F8: 155 | G8: 123 | H8: 32 | I8: 38 | J8: 1904 | K8: 2496.8 | L8: 60928 | M8: 1 | N8: 7 | O8: 4.1 | P8: 46051 | Q8: Low
A9: P075 | B9: Mixer 75 | C9: Home | D9: Bengaluru WH | E9: PrimeTrade | F9: 55 | G9: 35 | H9: 20 | I9: 71 | J9: 42026 | K9: 57778.29 | L9: 840520 | M9: 4 | N9: 11 | O9: 3.7 | P9: 46045 | Q9: Low
A10: P002 | B10: Laptop 2 | C10: Electronics | D10: Kolkata WH | E10: PrimeTrade | F10: 422 | G10: 149 | H10: 273 | I10: 45 | J10: 41324 | K10: 50082.01 | L10: 11281452 | M10: 5 | N10: 13 | O10: 4.3 | P10: 46063 | Q10: Normal
A11: P084 | B11: Laptop 84 | C11: Electronics | D11: Mumbai WH | E11: SupplyHub | F11: 416 | G11: 284 | H11: 132 | I11: 26 | J11: 57705 | K11: 80288.51 | L11: 7617060 | M11: 5 | N11: 10 | O11: 4.1 | P11: 46064 | Q11: Normal
A12: P041 | B12: Table 41 | C12: Furniture | D12: Bengaluru WH | E12: NovaSupply | F12: 459 | G12: 55 | H12: 404 | I12: 78 | J12: 42217 | K12: 46889.79 | L12: 17055668 | M12: 0 | N12: 5 | O12: 4.6 | P12: 46179 | Q12: Normal
A13: P073 | B13: Mixer 73 | C13: Home | D13: Kolkata WH | E13: TechCorp | F13: 383 | G13: 111 | H13: 272 | I13: 66 | J13: 37010 | K13: 48211.33 | L13: 10066720 | M13: 0 | N13: 12 | O13: 3.6 | P13: 46152 | Q13: Normal
... A801: P055 | B801: Chair 55 | C801: Furniture | D801: Kolkata WH | E801: PrimeTrade | F801: 84 | G801: 53 | H801: 31 | I801: 42 | J801: 59576 | K801: 67494.04 | L801: 1846856 | M801: 0 | N801: 15 | O801: 3.9 | P801: 46169 | Q801: Low

Sheet Order Dashboard

Sheet Inventory Dashboard

Sheet Sheet2
H8: Row Labels | I8: Sum of Sales_Amount | K8: Row Labels | L8: Sum of Sales_Amount | P8: TOTAL INVENTORY | Q8: =SUM(Inventory_Data!L:L) -> 3501388032
C9: Total Sales | F9: =SUM(Orders_Data!O2:O1201) -> 1.285515e+08 | H9: Electronics | I9: 51979378 | K9: West | L9: 36166622 | P9: CURRENT STOCK | Q9: =SUM(Inventory_Data!H:H) -> 110575
C10: Total Profit | F10: =SUM(Orders_Data!Q2:Q1201) -> 26569883 | H10: Fashion | I10: 22361289 | K10: North | L10: 35315601 | P10: LOW STOCK ITEM | Q10: =COUNTIF(Inventory_Data!Q:Q,"Low") -> 199
C11: Total Orders | F11: =COUNTA(Orders_Data!A2:A1201) -> 1200 | H11: Furniture | I11: 35609202 | K11: East | L11: 19237991 | P11: AVERAGE SUPPLY RATING | Q11: =AVERAGE(Inventory_Data!O:O) -> 4.2715
C12: Monthly Sales Trend | H12: Home | I12: 18601628 | K12: South | L12: 37831284
C13: Sales by Category | H13: Grand Total | I13: 1.285515e+08 | K13: Grand Total | L13: 1.285515e+08
C14: Sales by Region
C15: Payment Mode Distribution
C16: Online vs Offline Sales | P16: 1 stock by category
P17: 2 warehouse wise stock
C18: Top Products | P18: 3 stock status distribution
P19: 4 invtenory value by category
P20: 5 supplier rating
P21: 6 recorder level
C22: {=_xlfn.UNIQUE(Orders_Data!R2:R1201)} -> Card | D22: =SUMIF(Orders_Data!R2:R1201,Sheet2!C22,Orders_Data!O2:O1201) -> 44834765 | H22: Row Labels | I22: Sum of Sales_Amount | K22: {=_xlfn.UNIQUE(Orders_Data!J2:J1201)} -> Fashion | L22: {=_xlfn.UNIQUE(Orders_Data!K2:K1201)} -> Shoes | N22: =SUMIF(Orders_Data!K2:K1201,Sheet2!L22,Orders_Data!O2:O1201) -> 22361289
C23: UPI | D23: =SUMIF(Orders_Data!R3:R1202,Sheet2!C23,Orders_Data!O3:O1202) -> 43313306 | H23: Jan | I23: 22099242 | K23: Electronics | L23: Laptop | N23: =SUMIF(Orders_Data!K3:K1202,Sheet2!L23,Orders_Data!O3:O1202) -> 25229311
C24: Cash | D24: =SUMIF(Orders_Data!R4:R1203,Sheet2!C24,Orders_Data!O4:O1203) -> 40403426 | H24: Feb | I24: 20583786 | K24: Furniture | L24: Table | N24: =SUMIF(Orders_Data!K4:K1203,Sheet2!L24,Orders_Data!O4:O1203) -> 19088733 | P24: 1 | S24: 3 | V24: 4
H25: Mar | I25: 21674451 | K25: Home | L25: Chair | N25: =SUMIF(Orders_Data!K5:K1204,Sheet2!L25,Orders_Data!O5:O1204) -> 16520469 | P25: Row Labels | Q25: Sum of Current_Stock | S25: {=_xlfn.UNIQUE(Inventory_Data!Q2:Q801)} -> Normal | T25: =COUNTIF(Inventory_Data!Q2:Q801,"normal") -> 595 | V25: Electronics | W25: =SUMIF(Inventory_Data!C2:C801,Sheet2!V25,Inventory_Data!L2:L801) -> 1377056604 | X25: Row Labels | Y25: Sum of Inventory_Value
H26: Apr | I26: 21362115 | L26: Mobile | N26: =SUMIF(Orders_Data!K6:K1205,Sheet2!L26,Orders_Data!O6:O1205) -> 26750067 | P26: Electronics | Q26: 43296 | S26: Low | T26: =COUNTIF(Inventory_Data!Q3:Q802,"Low") -> 199 | V26: Fashion | W26: =SUMIF(Inventory_Data!C3:C802,Sheet2!V26,Inventory_Data!L3:L802) -> 524563735 | X26: Electronics | Y26: 1377056604
C27: ONLINE | D27: =SUMIF(Orders_Data!S2:S1201,Sheet2!C27,Orders_Data!O2:O1201) -> 58935605 | H27: May | I27: 24400840 | L27: Mixer | N27: =SUMIF(Orders_Data!K7:K1206,Sheet2!L27,Orders_Data!O7:O1206) -> 18601628 | P27: Fashion | Q27: 17065 | S27: Out | T27: =COUNTIF(Inventory_Data!Q4:Q803,"out") -> 6 | V27: Furniture | W27: =SUMIF(Inventory_Data!C4:C803,Sheet2!V27,Inventory_Data!L4:L803) -> 1034468318 | X27: Fashion | Y27: 524563735
C28: OFFLINE | D28: =SUMIF(Orders_Data!S3:S1202,Sheet2!C28,Orders_Data!O3:O1202) -> 69491152 | H28: Jun | I28: 18431063 | P28: Furniture | Q28: 32028 | V28: Home | W28: =SUMIF(Inventory_Data!C5:C804,Sheet2!V28,Inventory_Data!L5:L804) -> 565299375 | X28: Furniture | Y28: 1034468318
H29: Grand Total | I29: 1.285515e+08 | P29: Home | Q29: 18186 | X29: Home | Y29: 565299375
P30: Grand Total | Q30: 110575 | X30: Grand Total | Y30: 3501388032
U33: 5 | W33: 6
K34: category | L34: current stock | M34: inventory value | T34: {=_xlfn.UNIQUE(Inventory_Data!O2:O801)} -> 4.6 | U34: =COUNTIF(Inventory_Data!O:O,T34) -> 61
K35: Electronics | L35: =SUMIF(Inventory_Data!C2:C801,Sheet2!K35,Inventory_Data!H2:H801) -> 43296 | M35: =SUMIF(Inventory_Data!C2:C801,Sheet2!K35,Inventory_Data!L2:L801) -> 1377056604 | P35: 2 | T35: 3.8 | U35: =COUNTIF(Inventory_Data!O:O,T35) -> 42
K36: Fashion | L36: =SUMIF(Inventory_Data!C3:C802,Sheet2!K36,Inventory_Data!H3:H802) -> 17065 | M36: =SUMIF(Inventory_Data!C3:C802,Sheet2!K36,Inventory_Data!L3:L802) -> 524563735 | P36: {=_xlfn.UNIQUE(Inventory_Data!D2:D801)} -> Bengaluru WH | Q36: =SUMIF(Inventory_Data!D2:D801,Sheet2!P36,Inventory_Data!H2:H801) -> 28209 | T36: 4.1 | U36: =COUNTIF(Inventory_Data!O:O,T36) -> 56
K37: Furniture | L37: =SUMIF(Inventory_Data!C4:C803,Sheet2!K37,Inventory_Data!H4:H803) -> 32028 | M37: =SUMIF(Inventory_Data!C4:C803,Sheet2!K37,Inventory_Data!L4:L803) -> 1034468318 | P37: Kolkata WH | Q37: =SUMIF(Inventory_Data!D3:D802,Sheet2!P37,Inventory_Data!H3:H802) -> 26061 | T37: 4.9 | U37: =COUNTIF(Inventory_Data!O:O,T37) -> 56
K38: Home | L38: =SUMIF(Inventory_Data!C5:C804,Sheet2!K38,Inventory_Data!H5:H804) -> 18186 | M38: =SUMIF(Inventory_Data!C5:C804,Sheet2!K38,Inventory_Data!L5:L804) -> 565299375 | P38: Delhi WH | Q38: =SUMIF(Inventory_Data!D4:D803,Sheet2!P38,Inventory_Data!H4:H803) -> 29826 | T38: 4.2 | U38: =COUNTIF(Inventory_Data!O:O,T38) -> 54
P39: Mumbai WH | Q39: =SUMIF(Inventory_Data!D5:D804,Sheet2!P39,Inventory_Data!H5:H804) -> 26479 | T39: 3.7 | U39: =COUNTIF(Inventory_Data!O:O,T39) -> 51
T40: 4.3 | U40: =COUNTIF(Inventory_Data!O:O,T40) -> 66
T41: 3.6 | U41: =COUNTIF(Inventory_Data!O:O,T41) -> 51
T42: 3.9 | U42: =COUNTIF(Inventory_Data!O:O,T42) -> 50
O43: Row Labels | P43: Sum of Current_Stock | T43: 4.7 | U43: =COUNTIF(Inventory_Data!O:O,T43) -> 47
O44: NovaSupply | P44: 28835 | T44: 4.5 | U44: =COUNTIF(Inventory_Data!O:O,T44) -> 57
O45: PrimeTrade | P45: 25128 | T45: 4.8 | U45: =COUNTIF(Inventory_Data!O:O,T45) -> 53
O46: SupplyHub | P46: 30673 | T46: 4.4 | U46: =COUNTIF(Inventory_Data!O:O,T46) -> 62
O47: TechCorp | P47: 25939 | T47: 3.5 | U47: =COUNTIF(Inventory_Data!O:O,T47) -> 23
O48: Grand Total | P48: 110575 | T48: 4 | U48: =COUNTIF(Inventory_Data!O:O,T48) -> 45
T49: 5 | U49: =COUNTIF(Inventory_Data!O:O,T49) -> 26
